gnps2mhd/__init__.py
gnps2mhd/config.py
gnps2mhd/convertor_factory.py
gnps2mhd/commands/__init__.py
gnps2mhd/commands/cli.py
gnps2mhd/commands/create.py
gnps2mhd/commands/create_mhd_file.py
gnps2mhd/commands/fetch_gnps_study.py
gnps2mhd/commands/validate.py
gnps2mhd/v0_1/__init__.py
gnps2mhd/v0_1/utils.py
gnps2mhd/v0_1/legacy/__init__.py
gnps2mhd/v0_1/legacy/builder.py
gnps2mhd/v0_1/legacy/convertor.py
gnps2mhd/v0_1/ms/__init__.py
gnps2mhd/v0_1/ms/builder.py
gnps2mhd/v0_1/ms/convertor.py
gnps_mhd_integration-0.0.9.dist-info/licenses/LICENSE
gnps_mhd_integration-0.0.9.dist-info/METADATA
gnps_mhd_integration-0.0.9.dist-info/WHEEL
gnps_mhd_integration-0.0.9.dist-info/entry_points.txt
gnps_mhd_integration-0.0.9.dist-info/top_level.txt
gnps_mhd_integration-0.0.9.dist-info/RECORD
